wkflws/__init__.py
wkflws/conf.py
wkflws/credentials.py
wkflws/exceptions.py
wkflws/http.py
wkflws/logging.py
wkflws/workflow.py
wkflws/events/__init__.py
wkflws/executors/__init__.py
wkflws/executors/base.py
wkflws/executors/lambda.py
wkflws/executors/mp.py
wkflws/intrinsic_funcs/__init__.py
wkflws/intrinsic_funcs/environment.py
wkflws/intrinsic_funcs/exceptions.py
wkflws/intrinsic_funcs/expr.py
wkflws/intrinsic_funcs/funcs.py
wkflws/intrinsic_funcs/interpreter.py
wkflws/intrinsic_funcs/intrinsic_callable.py
wkflws/intrinsic_funcs/parser.py
wkflws/intrinsic_funcs/scanner.py
wkflws/intrinsic_funcs/stmt.py
wkflws/intrinsic_funcs/token.py
wkflws/intrinsic_funcs/tokentype.py
wkflws/lookup/__init__.py
wkflws/lookup/filesystem.py
wkflws/triggers/__init__.py
wkflws/triggers/base.py
wkflws/triggers/consumer.py
wkflws/triggers/producer.py
wkflws/triggers/webhook.py
wkflws/utils/__init__.py
wkflws/utils/execution.py
wkflws/utils/jsonpath.py
wkflws-0.1.2.data/scripts/wkflws
wkflws-0.1.2.dist-info/LICENSE
wkflws-0.1.2.dist-info/METADATA
wkflws-0.1.2.dist-info/WHEEL
wkflws-0.1.2.dist-info/top_level.txt
wkflws-0.1.2.dist-info/RECORD
